tests/__init__.py
tests/test_toop.py
toop/__init__.py
toop/main.py
toop/monitor.py
toop/toop.dat
toop/bin/toop_script.py
toop-0.2.data/scripts/toop_script.py
toop-0.2.dist-info/LICENSE.txt
toop-0.2.dist-info/METADATA
toop-0.2.dist-info/WHEEL
toop-0.2.dist-info/top_level.txt
toop-0.2.dist-info/RECORD
